src/__init__.py
src/__version__.py
src/api/__init__.py
src/api/api.py
src/api/protocols/__init__.py
src/api/protocols/code_review_response.py
src/api/router.py
src/api/v1/__init__.py
src/api/v1/code_review_controller.py
src/cli.py
src/core/__init__.py
src/core/agents/__init__.py
src/core/agents/code_review_agent.py
src/core/exceptions/__init__.py
src/core/exceptions/mergerequest_bad_request_exception.py
src/core/exceptions/mergerequest_not_found_exception.py
src/core/exceptions/prompt_not_found_exception.py
src/core/generativeai/__init__.py
src/core/generativeai/generative_ia_client.py
src/core/generativeai/jtech_vertexai.py
src/core/generativeai/vertex.py
src/core/gitlab/__init__.py
src/core/gitlab/group/__init__.py
src/core/gitlab/group/group_services.py
src/core/gitlab/mergerequest/__init__.py
src/core/gitlab/mergerequest/merge_request_service.py
src/core/gitlab/project/__init__.py
src/core/gitlab/project/projects_service.py
src/core/mongo/__init__.py
src/core/mongo/prompt_repository.py
src/core/mongo/review_repository.py
src/core/services/__init__.py
src/core/services/code_review_service.py
src/infra/__init__.py
src/infra/config/__init__.py
src/infra/config/constants.py
src/infra/config/logging_config.py
src/infra/config/settings.py
src/infra/di/__init__.py
src/infra/di/dependency_container.py
src/infra/gitlab/__init__.py
src/infra/gitlab/gitlab_config.py
src/infra/redis/__init__.py
src/infra/redis/jtech_redis.py
src/infra/utils/__init__.py
src/infra/utils/extract.py
src/infra/utils/pdf_reader.py
src/infra/utils/txt_reader.py
src/local_server.py
src/main.py
jtech_code_reviewer-1.0.1.dist-info/METADATA
jtech_code_reviewer-1.0.1.dist-info/WHEEL
jtech_code_reviewer-1.0.1.dist-info/entry_points.txt
jtech_code_reviewer-1.0.1.dist-info/RECORD
