Metadata-Version: 2.3
Name: jtech-code-reviewer
Version: 1.0.1
Summary: 
Author: Angelo Vicente Filho
Author-email: angelo.vicente@veolia.com
Requires-Python: >=3.10,<4.0
Classifier: Programming Language :: Python :: 3
Classifier: Programming Language :: Python :: 3.10
Classifier: Programming Language :: Python :: 3.11
Classifier: Programming Language :: Python :: 3.12
Classifier: Programming Language :: Python :: 3.13
Requires-Dist: build (>=1.0.3,<2.0.0)
Requires-Dist: colorlog (>=6.9.0,<7.0.0)
Requires-Dist: fastapi (>=0.115.4,<0.116.0)
Requires-Dist: langchain (>=0.3.6,<0.4.0)
Requires-Dist: langchain-community (>=0.3.4,<0.4.0)
Requires-Dist: langchain-google-genai (>=2.0.3,<3.0.0)
Requires-Dist: langchain-google-vertexai (>=2.0.7,<3.0.0)
Requires-Dist: python-dotenv (>=1.0.1,<2.0.0)
Requires-Dist: pyyaml (>=6.0.2,<7.0.0)
Requires-Dist: twine (>=4.0.2,<5.0.0)
Requires-Dist: uvicorn (>=0.32.0,<0.33.0)
Requires-Dist: wheel (>=0.42.0,<0.43.0)
Project-URL: documentation, https://github.com/your-username/jtech-code-review#readme
Project-URL: repository, https://github.com/your-username/jtech-code-review
